{
  "id": "devconnect-2025-the-official-recap-by-ech-institute-or-key-moments-and-community-highlights-2",
  "sourceId": "N64FlANVK8U",
  "eventId": "devconnect-arg",
  "title": "Devconnect 2025: The Official Recap by ECH Institute | Key Moments & Community Highlights",
  "description": "🇦🇷 Experience the Energy of Devconnect 2025 with ECH Institute!\n\nA quick recap from the ECH Institute capturing the vibrant energy of Buenos Aires - from deep technical talks and hands-on workshops to insightful interviews and community moments. A memorable journey of Devconnect 2025, reliving the highlights that brought the ecosystem together.\n\nDevconnect Related Content\n - https://youtu.be/yEn-gDIa56I\n - https://youtu.be/aPPV6HhleWQ\n - https://youtu.be/iJjWMJdYqFw\n - https://youtu.be/RQC8yjBnUGw\n - https://youtu.be/wH76j1BDZkc\n - https://youtu.be/ZVHHsKS6Kxo\n - https://youtu.be/i8HO-bAivno\n - https://youtu.be/9yTrzNCd0Gk\n - https://youtu.be/h5sUMWD9Yus\n - https://youtu.be/HpRNP8tc0lY\n - https://youtu.be/WcGYlzUChUE\n - https://youtu.be/RaeBZiE0rDA\n - https://youtu.be/YHZviU19di0\n - https://youtu.be/_szGTp49L5E\n\nOfficial Websites:\nECH Institute: https://echinstitute.org/\n\n🔗 Follow ECH Institute\nX/Twitter: https://twitter.com/echinstitute\nWarpcast: https://warpcast.com/ethcatherders\nMedium: https://medium.com/ethereum-cat-herders\nDiscord: https://discord.gg/H2eYpKCxxm\n\n💸 Support ECH Institute\nDonate: https://www.ethcatherders.com/donate\n\nCredits: 🎥 Video Edited by: Akash – https://twitter.com/lookupforsky\n\n#devconnect2025 #recap #ethereum #event",
  "track": "EIP Summit",
  "type": "Talk",
  "expertise": "",
  "tags": [],
  "speakers": [],
  "sources_youtubeId": "N64FlANVK8U",
  "duration": 67,
  "language": "en"
}
