{
  "id": "noir-10-with-savio-sou-or-noircon-3-devconnect-2025",
  "sourceId": "dniKElkMps8",
  "eventId": "devconnect-arg",
  "title": "Noir 1.0 with Savio Sou | NoirCon 3 Devconnect 2025",
  "description": "Noir is approaching its first major release.\n\nIn this talk, Savio Sou, Noir Product Manager, walks through Noir 1.0 and what to expect from the release. \n\nConnect with socials\nAztec Network X: https://x.com/aztecnetwork\nNoir X: https://x.com/NoirLang\nAztec Foundation X: https://x.com/aztecFND\nAztec Website: https://aztec.network/\nBlog: https://aztec.network/blog\nAztec Discord:  https://discord.gg/aztec\n\nFor the devs:\nhttps://noir-lang.org/docs\nhttps://noir-lang.org/\n\n#aztecnetwork #noir #zk #privacy #ethereum #devconnect",
  "track": "NoirCon 3",
  "type": "Talk",
  "expertise": "",
  "tags": [],
  "speakers": [],
  "sources_youtubeId": "dniKElkMps8",
  "duration": 1853,
  "language": "en"
}
