{
  "id": "bridging-tradfi-and-defi-through-ethereum-and-evm-a-pathway-to-innovation",
  "sourceId": "8N3GEZ",
  "title": "Bridging TradFi and DeFi through Ethereum and EVM: A Pathway to Innovation",
  "description": "This workshop will explore how Ethereum and EVM-based environments are becoming the critical intersection between traditional finance (TradFi) and decentralized finance (DeFi). It will focus on Ethereum’s maturity for real-world use cases, the role of EVM in regulated environments, and how institutions, governments, and central banks can foster innovation by leveraging permissionless blockchains while maintaining compliance with regulations.",
  "track": "Real World Ethereum",
  "type": "Workshop",
  "expertise": "Beginner",
  "audience": "Business",
  "featured": false,
  "doNotRecord": false,
  "keywords": [
    "Tokenization",
    "CBDC",
    "RWA"
  ],
  "tags": [
    "Public good",
    "RWA"
  ],
  "language": "en",
  "speakers": [
    "bruno-batavia"
  ],
  "eventId": "devcon-7",
  "slot_start": "2024-11-12T05:30:00.000Z",
  "slot_end": "2024-11-12T07:30:00.000Z",
  "slot_roomId": "classroom-d"
}