{
  "id": "eve-frontier-challenges-lessons-and-future-of-building-an-autonomous-world-on-ethereum",
  "sourceId": "QLK8UE",
  "title": "EVE Frontier - challenges, lessons and future of building an autonomous world on Ethereum",
  "description": "CCP Games—the creators of the legendary space-based MMO EVE Online, home to millions of space merchants, pirates, and explorers—is building a new world, and it is going to live onchain and run on the EVM.\r\n\r\nHear from the CCP team as they discuss challenges, learnings, and open questions of building massive virtual worlds onchain—what to put onchain first? What game mechanics are best suited onchain? What are the unlocks?—as well as what EVE Frontier might bring to the Ethereum ecosystem.",
  "track": "Real World Ethereum",
  "type": "Talk",
  "expertise": "Beginner",
  "audience": "Engineering",
  "featured": false,
  "doNotRecord": false,
  "keywords": [
    "MUD",
    "EVE Frontier",
    "EVE Online"
  ],
  "tags": [
    "Gaming",
    "Autonomous World",
    "eve",
    "online",
    "Autonomous World",
    "Gaming"
  ],
  "language": "en",
  "speakers": [
    "justin-glibert",
    "hilmar-petursson"
  ],
  "eventId": "devcon-7",
  "slot_start": 1731468600000,
  "slot_end": 1731470400000,
  "slot_roomId": "main-stage",
  "resources_presentation": "https://docs.google.com/presentation/d/1mqLIgd8le45XgG2FPsR3vi1IafiikIiEzC9TaHmFCvk"
}