{
  "id": "porting-dark-forest-to-mud-mud-day-demo",
  "sourceId": "VBS9CJ",
  "title": "Porting Dark Forest to MUD - MUD Day Demo",
  "description": "We recently ported Dark Forest to the MUD engine and would like to share some of the insights we gained during this process with everyone.",
  "track": "[CLS] MUD Community-Led Session, by 0xPARC",
  "type": "Lightning Talk",
  "expertise": "",
  "audience": "Engineering",
  "featured": false,
  "doNotRecord": false,
  "keywords": [],
  "tags": [],
  "language": "en",
  "speakers": [
    "ddy"
  ],
  "eventId": "devcon-7",
  "slot_start": 1731556200000,
  "slot_end": 1731556500000,
  "slot_roomId": "classroom-a",
  "resources_presentation": "https://docs.google.com/presentation/d/14aQQNVk55JWYMHYKeZITv12OkJVvgS-kWDNWXp6cpX4"
}