{
  "id": "the-end-game-wallet-when-does-abstraction-go-too-far",
  "sourceId": "ZTMLMQ",
  "title": "The End Game Wallet: When Does Abstraction Go Too Far?",
  "description": "Chain abstraction has taken the front seat. As innovations continue, it's becoming increasingly stark that we will eventually approach a world where third-party solvers fulfill most transactions. The core protocol is also changing to cater to further abstractions even at the validator level. The question remains, how far are we willing to go in the name of efficiency, and optimizations, to which a user can't use Ethereum without third parties?",
  "track": "Usability",
  "type": "Lightning Talk",
  "expertise": "Intermediate",
  "audience": "Engineering",
  "featured": false,
  "doNotRecord": false,
  "tags": [
    "Values",
    "UI/UX",
    "UI/UX",
    "Values"
  ],
  "keywords": [
    "n/a"
  ],
  "duration": 602,
  "language": "en",
  "sources_swarmHash": "bbf4c10d801934b671c122c84ecccd4d41134ab3102920d95762ec1e24fd214a",
  "sources_youtubeId": "FBB5YWMQ56s",
  "sources_ipfsHash": "",
  "sources_livepeerId": "",
  "sources_streamethId": "673579d19dbb7a90e1d1825d",
  "transcript_vtt": "No VTT link provided",
  "transcript_text": "No transcript text provided",
  "eventId": "devcon-7",
  "slot_start": 1731556800000,
  "slot_end": 1731557400000,
  "slot_roomId": "stage-4",
  "resources_presentation": "https://docs.google.com/presentation/d/1Yvp0nywauCOnCqYI14BUwqz77qWUB-SScBhTcicFGtg",
  "resources_slides": null,
  "speakers": [
    "gregthegreek"
  ]
}