{
  "id": "sikorka-proof-of-presence-for-blockchain-applications",
  "sourceId": "sikorka-proof-of-presence-for-blockchain-applications",
  "eventId": "devcon-3",
  "title": "Sikorka – Proof of Presence for Blockchain Applications",
  "description": "Sikorka – Proof of Presence for Blockchain Applications",
  "track": "Developer Experience",
  "type": "Talk",
  "expertise": "Intermediate",
  "tags": [
    "Developer Infrastructure"
  ],
  "speakers": [
    "lefteris-karapetsas"
  ],
  "sources_youtubeId": "XAs6_iV6gGQ",
  "sources_ipfsHash": "QmaF6My17nJrukwr6wkhbSfPKYt451aqbzy1X7ZhNfLrDn",
  "sources_swarmHash": "fda0178412c33938f695e49bb7d76b5d9c2bdaa7e5386068baedaec94971bb61",
  "duration": 832,
  "language": "en"
}